{
  "2025-05-28": {
    "volume": 1411,
    "sentiment": {
      "neutral": 499,
      "negative": 606,
      "positive": 306
    },
    "emotion": {
      "fear": 462,
      "sadness": 261,
      "neutral": 335,
      "anger": 109,
      "surprise": 68,
      "joy": 109,
      "disgust": 67
    },
    "language": {
      "en": 1146,
      "fr": 19,
      "da": 1,
      "ar": 6,
      "in": 1,
      "ja": 9,
      "eu": 1,
      "de": 12,
      "lt": 1,
      "en-US": 7,
      "nl": 7,
      "am": 1,
      "la": 2,
      "pt": 10,
      "th": 1,
      "es": 5,
      "ca": 1,
      "sv": 2,
      "it": 2,
      "en-GB": 1,
      "gd": 1,
      "ru": 1,
      "EN": 2
    }
  },
  "2025-05-30": {
    "volume": 5401,
    "sentiment": {
      "positive": 1113,
      "negative": 2463,
      "neutral": 1825
    },
    "emotion": {
      "joy": 401,
      "sadness": 1091,
      "surprise": 275,
      "neutral": 1190,
      "fear": 1663,
      "disgust": 266,
      "anger": 515
    },
    "language": {
      "en": 4545,
      "de": 37,
      "en-US": 39,
      "fr": 29,
      "sq": 2,
      "ar": 15,
      "cy": 1,
      "es": 16,
      "pt": 25,
      "ko": 7,
      "nl": 10,
      "it": 5,
      "en-us": 2,
      "ja": 21,
      "en-GB": 6,
      "fr-FR": 2,
      "jp": 1,
      "sv": 4,
      "pl": 2,
      "zh": 1,
      "la": 1,
      "id": 1,
      "ru": 2,
      "en-AU": 2,
      "cs": 1,
      "tr": 4,
      "nb": 1,
      "tl": 1,
      "ab": 1,
      "gl": 1
    }
  },
  "2025-05-31": {
    "volume": 1132,
    "sentiment": {
      "negative": 545,
      "positive": 233,
      "neutral": 354
    },
    "emotion": {
      "anger": 102,
      "sadness": 270,
      "fear": 324,
      "surprise": 62,
      "neutral": 223,
      "joy": 85,
      "disgust": 66
    },
    "language": {
      "en": 979,
      "en-AU": 1,
      "nb": 1,
      "no": 1,
      "la": 4,
      "en-US": 13,
      "ja": 1,
      "pt": 2,
      "tl": 1,
      "en-GB": 1,
      "id": 2,
      "es": 5,
      "vi": 1,
      "fr": 2,
      "zh-CN": 1,
      "zh-HK": 1,
      "zh-TW": 1,
      "de": 4,
      "de-DE": 1
    }
  },
  "2025-06-01": {
    "volume": 4409,
    "sentiment": {
      "positive": 955,
      "negative": 2063,
      "neutral": 1391
    },
    "emotion": {
      "fear": 1348,
      "joy": 393,
      "anger": 375,
      "neutral": 899,
      "surprise": 231,
      "sadness": 932,
      "disgust": 231
    },
    "language": {
      "en": 3693,
      "de": 35,
      "en-US": 34,
      "ja": 20,
      "pt": 28,
      "fr": 26,
      "fr-FR": 3,
      "ar": 58,
      "fi": 1,
      "sv": 3,
      "av": 2,
      "es": 19,
      "ko": 5,
      "en-AU": 3,
      "la": 3,
      "nl": 4,
      "zh": 5,
      "id": 3,
      "tr": 2,
      "th": 2,
      "en-GB": 5,
      "af": 1,
      "ak": 1,
      "cs": 1,
      "it": 3,
      "ht": 1,
      "ga": 1,
      "uk": 1,
      "ca": 1,
      "sr": 1,
      "ru": 1,
      "eu": 1,
      "sq": 1,
      "am": 1
    }
  },
  "2025-06-02": {
    "volume": 4986,
    "sentiment": {
      "negative": 2451,
      "positive": 1053,
      "neutral": 1482
    },
    "emotion": {
      "neutral": 1050,
      "sadness": 1149,
      "fear": 1524,
      "surprise": 252,
      "joy": 421,
      "disgust": 217,
      "anger": 373
    },
    "language": {
      "en": 3917,
      "de": 41,
      "ar": 222,
      "es": 24,
      "ro": 2,
      "ja": 27,
      "fr": 43,
      "en-US": 41,
      "it": 6,
      "vi": 1,
      "nb": 2,
      "pt": 28,
      "th": 2,
      "ko": 7,
      "ga": 1,
      "he": 1,
      "nl": 9,
      "en-GB": 4,
      "pl": 2,
      "fr-FR": 1,
      "zh": 1,
      "ru": 6,
      "ay": 1,
      "sv": 2,
      "id": 1,
      "ms": 1,
      "en-AU": 1,
      "tr": 1,
      "da": 3,
      "ca": 1,
      "af": 1,
      "av": 1,
      "eu": 2,
      "tl": 2,
      "sq": 1,
      "uk": 1,
      "fi": 1,
      "pt-BR": 1
    }
  }
}