{
  "topic_0": {
    "neutral": 124,
    "negative": 205,
    "positive": 95
  },
  "topic_7": {
    "negative": 88,
    "positive": 33,
    "neutral": 89
  },
  "topic_3": {
    "neutral": 109,
    "negative": 89,
    "positive": 41
  },
  "topic_4": {
    "negative": 56,
    "positive": 37,
    "neutral": 55
  },
  "topic_5": {
    "neutral": 40,
    "negative": 69,
    "positive": 25
  },
  "topic_6": {
    "positive": 18,
    "negative": 29,
    "neutral": 16
  },
  "topic_1": {
    "negative": 30,
    "positive": 43,
    "neutral": 51
  },
  "topic_2": {
    "negative": 40,
    "neutral": 16,
    "positive": 14
  }
}